{"layout":"article.njk","title":"Introducing ImageUpscalerAI: An AI-Powered Image Upscaling Tool","date":"2023-06-21T03:00:00.000Z","formattedDate":"2023-6-21","source_link":"https://imageupscalerai.com/","tags":["ai"],"topics":[{"name":"AI","slug":"ai"}],"content":"<p>ImageUpscalerAI is an AI-powered tool that allows users to easily and quickly upscale their images, photos, cartoons, and more. This tool uses artificial intelligence to enhance the quality of images, making them look sharper and more detailed. </p>\n<p>One of the key features of ImageUpscalerAI is its ease of use. The tool is simple and straightforward, making it accessible to both novice and experienced users. All users need to do is upload their images to the website, and the tool takes care of the rest. </p>\n<p>Another great feature of ImageUpscalerAI is its speed. The tool is designed to upscale images quickly, allowing users to get their enhanced images in no time. Additionally, users can upscale multiple images at once, saving them time and effort. </p>\n<p>ImageUpscalerAI is powered by a fork of imaginAIry, a popular open-source library for image processing. The project is developed using Django, a high-level Python web framework, which allows for easy maintenance and scalability. </p>\n<p>Privacy and security are also a top priority for ImageUpscalerAI. The tool ensures that all uploaded images are deleted after 24 hours, and it offers a privacy policy and terms of service to protect user data. </p>\n<p>For developers interested in working with AI-powered image processing, ImageUpscalerAI offers a great opportunity to learn and experiment. The tool&#39;s use of imaginAIry and Django makes it a great example of how these technologies can be used together to create powerful applications. </p>\n<p>Here&#39;s an example of how to use ImageUpscalerAI in Python:</p>\n<pre><code>import requests\nimport base64\n\n# Encode image as base64\nwith open(&quot;image.jpg&quot;, &quot;rb&quot;) as image_file:\n    encoded_string = base64.b64encode(image_file.read()).decode(&#39;utf-8&#39;)\n\n# Send request to API\nurl = &quot;https://api.imageupscalerai.com/upscale&quot;\npayload = {&quot;image&quot;: encoded_string}\nheaders = {&quot;Authorization&quot;: &quot;Bearer YOUR_API_KEY&quot;}\nresponse = requests.post(url, json=payload, headers=headers)\n\n# Save upscaled image\nwith open(&quot;upscaled_image.jpg&quot;, &quot;wb&quot;) as image_file:\n    image_file.write(base64.b64decode(response.json()[&quot;image&quot;]))\n</code></pre>\n<p>In conclusion, ImageUpscalerAI is a powerful and easy-to-use tool for anyone looking to enhance the quality of their images. Its use of AI and open-source technologies makes it a great example of how developers can leverage these tools to create innovative applications.</p>\n"}